{
    "src_flash_array_host": "source_flash_array.localdomain",
    "src_flash_array_api_token": "itsasecret",
    "rescan_scsi_bus": "sudo /root/udev/rescan_udev.sh",
    "src_protection_group": "gct-oradb-rdmudev01-pg",
    "tgt_protection_group": "gct-oradb-rdmudev02-pg",
    "oracle_target_mode": "DOWN",
    "local_listener": "(ADDRESS=(PROTOCOL=TCP)(HOST=targte_host.localdomain)(PORT=1521))",

    "ora_src_usr": "sys",
    "ora_src_pwd": "change_on_install",
    "ora_src_cs": "gct-oradb-rdmudev01:1521/swingdb",
    "ora_backup_mode": "False",

    "def_user_oracle": "oracle",
    "def_passwd_oracle": "itsasecret",
    "def_user_grid": "oracle",
    "def_passwd_grid": "itsasecret",
    "def_asm": "+ASM",
    "def_port": "22",
    "def_cs_db": "connect / as sysdba",
    "def_cs_asm": "connect / as sysasm",

    "tgt_host": "gct-oradb-rdmudev02",
    "tgt_db": "swingdb",
    "tgt_user_grid": "oracle",
    "tgt_pass_grid": "itsasecret",
    "tgt_sid": "swingdev"

}
